simulatrex/__init__.py
simulatrex/agent.py
simulatrex/config.py
simulatrex/db.py
simulatrex/engine.py
simulatrex/environment.py
simulatrex/evaluation.py
simulatrex/event.py
simulatrex/memory.py
simulatrex/target_group.py
simulatrex/vectordb.py
simulatrex/agent_utils/__init__.py
simulatrex/agent_utils/converse.py
simulatrex/agent_utils/perceive.py
simulatrex/agent_utils/spawn.py
simulatrex/agent_utils/think.py
simulatrex/agent_utils/types.py
simulatrex/llm_utils/__init__.py
simulatrex/llm_utils/models.py
simulatrex/llm_utils/prompts.py
simulatrex/llm_utils/prompt_templates/agent_converse.txt
simulatrex/llm_utils/prompt_templates/agent_decide_on_conversation.txt
simulatrex/llm_utils/prompt_templates/agent_evaluation.txt
simulatrex/llm_utils/prompt_templates/agent_identity_spawn.txt
simulatrex/llm_utils/prompt_templates/agent_interview.txt
simulatrex/llm_utils/prompt_templates/agent_perception.txt
simulatrex/llm_utils/prompt_templates/agent_reply_to_conversation.txt
simulatrex/llm_utils/prompt_templates/agent_start_conversation.txt
simulatrex/llm_utils/prompt_templates/agent_think.txt
simulatrex/llm_utils/prompt_templates/evaluate_agent_outputs.txt
simulatrex/llm_utils/prompt_templates/summarize_environment.txt
simulatrex/utils/__init__.py
simulatrex/utils/json_utils.py
simulatrex/utils/log.py
simulatrex/utils/time_utils.py
simulatrex-0.0.4.1.dist-info/LICENSE
simulatrex-0.0.4.1.dist-info/METADATA
simulatrex-0.0.4.1.dist-info/WHEEL
simulatrex-0.0.4.1.dist-info/top_level.txt
simulatrex-0.0.4.1.dist-info/RECORD
