Metadata-Version: 2.1
Name: simulatrex
Version: 0.0.4.1
Summary: LLM-based simulation framework
Home-page: https://github.com/simulatrex/simulatrex
Author: Dominik Scherm
Author-email: me@dominikscherm.de
License-File: LICENSE
Requires-Dist: openai
Requires-Dist: uuid
Requires-Dist: pandas
Requires-Dist: termcolor
Requires-Dist: chromadb
Requires-Dist: pydantic
Requires-Dist: python-dotenv
Requires-Dist: requests
Requires-Dist: instructor
Requires-Dist: SQLAlchemy
